govee_api_ble/__init__.py
govee_api_ble/device.py
govee_api_ble-0.0.9.dist-info/LICENSE
govee_api_ble-0.0.9.dist-info/METADATA
govee_api_ble-0.0.9.dist-info/WHEEL
govee_api_ble-0.0.9.dist-info/top_level.txt
govee_api_ble-0.0.9.dist-info/RECORD
