Metadata-Version: 2.1
Name: govee-api-ble
Version: 0.0.9
Summary: Python API for Govee H6127 RGB lighting strips 
Home-page: https://github.com/softgrass/govee-api-ble
Author: Cyprus Snodgrass
Author-email: soft@null.net
Project-URL: Bug Tracker, https://github.com/softgrass/govee-api-ble/issues
Classifier: Programming Language :: Python :: 3
Classifier: License :: OSI Approved :: MIT License
Classifier: Operating System :: OS Independent
Requires-Python: >=3.7
License-File: LICENSE
